hoist/__about__.py
hoist/__init__.py
hoist/__main__.py
hoist/_client_ws.py
hoist/_errors.py
hoist/_html.py
hoist/_logging.py
hoist/_messages.py
hoist/_operations.py
hoist/_schema.py
hoist/_socket.py
hoist/_typing.py
hoist/_uvicorn.py
hoist/_warnings.py
hoist/client.py
hoist/exceptions.py
hoist/message.py
hoist/py.typed
hoist/server.py
hoist/utils.py
hoist_http-1.0.1.dist-info/METADATA
hoist_http-1.0.1.dist-info/WHEEL
hoist_http-1.0.1.dist-info/entry_points.txt
hoist_http-1.0.1.dist-info/licenses/LICENSE
hoist_http-1.0.1.dist-info/RECORD
