Metadata-Version: 2.1
Name: hoist-http
Version: 1.0.1
Summary: Easy client-server communication
Project-URL: Documentation, https://hoist.zintensity.dev
Project-URL: Issues, https://github.com/ZeroIntensity/hoist/issues
Project-URL: Source, https://github.com/ZeroIntensity/hoist
Author-email: ZeroIntensity <zintensitydev@gmail.com>
Classifier: Development Status :: 4 - Beta
Classifier: Programming Language :: Python
Classifier: Programming Language :: Python :: 3.7
Classifier: Programming Language :: Python :: 3.8
Classifier: Programming Language :: Python :: 3.9
Classifier: Programming Language :: Python :: 3.10
Requires-Python: >=3.7
Requires-Dist: aiohttp>=3.8.1
Requires-Dist: click>=8.1.3
Requires-Dist: rich>=12.5.1
Requires-Dist: starlette>=0.20.4
Requires-Dist: typing-extensions>=4.3.0
Requires-Dist: uvicorn[standard]>=0.18.2
Requires-Dist: versions>=1.1.0
Requires-Dist: yarl>=1.7.2
